pyFormal/__init__.py
pyFormal/images2grid.py
pyFormal/squareVideo2RoundedVideo.py
pyFormal/utils.py
pyFormal-0.1.7.dist-info/METADATA
pyFormal-0.1.7.dist-info/WHEEL
pyFormal-0.1.7.dist-info/entry_points.txt
pyFormal-0.1.7.dist-info/top_level.txt
pyFormal-0.1.7.dist-info/RECORD
