Metadata-Version: 2.1
Name: pyFormal
Version: 0.1.7
Summary: An application to create a grid of nicely formatted images from a folder of images.
Home-page: https://github.com/malekinho8/pyFormal
Author: Malek
Author-email: shmeek8@gmail.com
Classifier: Programming Language :: Python :: 3
Classifier: Programming Language :: Python :: 3.8
Requires-Dist: pyperclip
Requires-Dist: matplotlib
Requires-Dist: numpy
Requires-Dist: click
Requires-Dist: Pillow
Requires-Dist: pillow-heif
